devices/__init__.py
devices/devices.py
devices/zlg/__init__.py
devices/zlg/main.py
devices/zlg/zlgcan.py
devices/zlg/zlgcan_demo.py
framework/__init__.py
framework/canbox.py
framework/canbus.py
framework/candb.py
framework/canfactory.py
framework/canmsg.py
framework/cansignal.py
framework/concurrentcanbox.py
framework/glue.py
framework/nodes.py
framework/trigger.py
LearnPythonPackaging-0.0.1.dist-info/LICENSE
LearnPythonPackaging-0.0.1.dist-info/METADATA
LearnPythonPackaging-0.0.1.dist-info/WHEEL
LearnPythonPackaging-0.0.1.dist-info/top_level.txt
LearnPythonPackaging-0.0.1.dist-info/RECORD
