Metadata-Version: 2.1
Name: LearnPythonPackaging
Version: 0.0.1
Summary: Learn Python Packaging
Home-page: https://github.com/pypa/sampleproject
Author: chenhewen
Author-email: chenhewen@example.com
License: UNKNOWN
Platform: UNKNOWN
Classifier: Programming Language :: Python :: 3
Classifier: License :: OSI Approved :: MIT License
Classifier: Operating System :: OS Independent
Requires-Python: >=3.6
